spark/__init__.py
spark/__main__.py
spark/autotag.py
spark/cli.py
spark/database.py
spark_cli-0.4.1.dist-info/licenses/LICENSE
spark_cli-0.4.1.dist-info/METADATA
spark_cli-0.4.1.dist-info/WHEEL
spark_cli-0.4.1.dist-info/entry_points.txt
spark_cli-0.4.1.dist-info/top_level.txt
spark_cli-0.4.1.dist-info/RECORD
